{
  "name": "cvoaz01",
  "tenantId": "{YOUR_NETAPP_WORKSPACE_ID}",
  "region": "eastus2",
  "packageName": "azure_poc",
  "dataEncryptionType": "AZURE",
  "capacityTier": "Blob",
  "vsaMetadata": {
    "ontapVersion": "ONTAP-9.10.1RC1.T1.azure",
    "licenseType": "capacity-paygo",
    "instanceType": "Standard_E4s_v3",
    "capacityPackageName": "Freemium"
  },
  "nssAccount": "{YOUR_NSS_ACCOUNT_ID}",
  "writingSpeedState": "NORMAL",
  "subnetId": "/subscriptions/{YOUR_AZURE_SUBCRIPTION_ID}/resourceGroups/{YOUR_RG_NAME}/providers/Microsoft.Network/virtualNetworks/{YOUR_VNET}/subnets/{YOUR_SUBNET}",
  "svmPassword": "Netapp234",
  "vnetId": "/subscriptions/{YOUR_AZURE_SUBSCRIPOINT_ID}/resourceGroups/{YOUR_RG_NAME}/providers/Microsoft.Network/virtualNetworks/{YOUR_VNET}",
  "cidr": "172.30.16.0/20",
  "ontapEncryptionParameters": null,
  "skipSnapshots": false,
  "diskSize": {
    "size": 500,
    "unit": "GB",
    "_identifier": "500 GB"
  },
  "storageType": "Premium_LRS",
  "azureTags": [],
  "subscriptionId": "{YOUR_AZURE_SUBSCRIPOINT_ID}",
  "cloudProviderAccount": "{YOUR_AZURE_ACCOUNT_ID}",
  "backupVolumesToCbs": false,
  "enableCompliance": false,
  "enableMonitoring": false,
  "availabilityZone": 1,
  "resourceGroup": "cvoaz01-rg"
}
